lk_qtquick_scaffold/__init__.py
lk_qtquick_scaffold/__main__.py
lk_qtquick_scaffold/application.py
lk_qtquick_scaffold/experimental_features/acrylic_window.py
lk_qtquick_scaffold/experimental_features/win11_mica_material.py
lk_qtquick_scaffold/pyside/__init__.py
lk_qtquick_scaffold/pyside/pyside.py
lk_qtquick_scaffold/pyside/register.py
lk_qtquick_scaffold/qmlside/__init__.py
lk_qtquick_scaffold/qmlside/assets.py
lk_qtquick_scaffold/qmlside/broadcast.py
lk_qtquick_scaffold/qmlside/hot_reloader/__init__.py
lk_qtquick_scaffold/qmlside/hot_reloader/__main__.py
lk_qtquick_scaffold/qmlside/hot_reloader/hot_reloader.py
lk_qtquick_scaffold/qmlside/hot_reloader/legacy_view.qml
lk_qtquick_scaffold/qmlside/hot_reloader/requirements.txt
lk_qtquick_scaffold/qmlside/hot_reloader/view.qml
lk_qtquick_scaffold/qmlside/js_evaluator.py
lk_qtquick_scaffold/qmlside/js_evaluator_core.qml
lk_qtquick_scaffold/qmlside/layout_helper/__init__.py
lk_qtquick_scaffold/qmlside/layout_helper/anchors.py
lk_qtquick_scaffold/qmlside/layout_helper/container_alignment.py
lk_qtquick_scaffold/qmlside/layout_helper/content_alignment.py
lk_qtquick_scaffold/qmlside/layout_helper/layout_helper.py
lk_qtquick_scaffold/qmlside/model.py
lk_qtquick_scaffold/qmlside/qlogger.py
lk_qtquick_scaffold/qmlside/resource_manager/__init__.py
lk_qtquick_scaffold/qmlside/resource_manager/assets.py
lk_qtquick_scaffold/qmlside/resource_manager/base.py
lk_qtquick_scaffold/qmlside/resource_manager/color.py
lk_qtquick_scaffold/qmlside/resource_manager/control.py
lk_qtquick_scaffold/qmlside/resource_manager/layout.py
lk_qtquick_scaffold/qmlside/resource_manager/motion.py
lk_qtquick_scaffold/qmlside/resource_manager/shape.py
lk_qtquick_scaffold/qmlside/resource_manager/text.py
lk_qtquick_scaffold/qmlside/widgets_backend/__ext__.py
lk_qtquick_scaffold/qmlside/widgets_backend/__init__.py
lk_qtquick_scaffold/qmlside/widgets_backend/listview.py
lk_qtquick_scaffold/qmlside/widgets_backend/progress.py
lk_qtquick_scaffold-2.0.0.dist-info/WHEEL
lk_qtquick_scaffold-2.0.0.dist-info/METADATA
lk_qtquick_scaffold-2.0.0.dist-info/RECORD
