Metadata-Version: 2.1
Name: lk-qtquick-scaffold
Version: 2.0.0
Summary: A flexible toolset to improve QML coding experience for PyQt/PySide development.
Home-page: https://github.com/likianta/lk-qtquick-scaffold
License: MIT
Author: Likianta
Author-email: likianta@foxmail.com
Requires-Python: >=3.8,<4.0
Classifier: License :: OSI Approved :: MIT License
Classifier: Programming Language :: Python :: 3
Classifier: Programming Language :: Python :: 3.10
Classifier: Programming Language :: Python :: 3.8
Classifier: Programming Language :: Python :: 3.9
Provides-Extra: qt5
Provides-Extra: qt6
Requires-Dist: argsense (>=0.4.2,<0.5.0)
Requires-Dist: lambda-ex (>=1.1.0,<2.0.0)
Requires-Dist: lk-logger (>=5.4.1,<6.0.0)
Requires-Dist: lk-utils (>=2.4.0,<3.0.0)
Requires-Dist: pyside2; extra == "qt5"
Requires-Dist: pyside6; extra == "qt6"
Requires-Dist: pyyaml
Requires-Dist: qtpy
